isg/Databases.py
isg/Feature_Correlation.py
isg/Plotting.py
isg/Preprocessing.py
isg/__init__.py
AuSeSol_isg-1.0.1.dist-info/LICENSE
AuSeSol_isg-1.0.1.dist-info/METADATA
AuSeSol_isg-1.0.1.dist-info/WHEEL
AuSeSol_isg-1.0.1.dist-info/top_level.txt
AuSeSol_isg-1.0.1.dist-info/RECORD
